{
  "EditionName": "TOIMumbai",
  "PageName": "30_09_2022_204_toim.jpg",
  "PageWidth": 989,
  "PageHeight": 1540,
  "PageContent": [
    {
      "ArticleName": "30_09_2022_204_001_toim",
      "Zones": [
        {
          "TagName": "Advertisement",
          "X": 24,
          "Y": 864,
          "W": 367,
          "H": 51,
          "ZoneId": "30_09_2022_204_001_001"
        }
      ]
    },
    {
      "ArticleName": "30_09_2022_204_002_toim",
      "Zones": [
        {
          "TagName": "Article Title",
          "X": 578,
          "Y": 497,
          "W": 384,
          "H": 138,
          "ZoneId": "30_09_2022_204_002_006"
        },
        {
          "TagName": "Article Body",
          "X": 584,
          "Y": 630,
          "W": 192,
          "H": 392,
          "ZoneId": "30_09_2022_204_002_008"
        },
        {
          "TagName": "Article Body",
          "X": 774,
          "Y": 958,
          "W": 197,
          "H": 66,
          "ZoneId": "30_09_2022_204_002_009"
        },
        {
          "TagName": "Photographs",
          "X": 722,
          "Y": 624,
          "W": 240,
          "H": 332,
          "ZoneId": "30_09_2022_204_002_010"
        },
        {
          "TagName": "Author",
          "X": 904,
          "Y": 1011,
          "W": 66,
          "H": 14,
          "ZoneId": "30_09_2022_204_002_007"
        },
        {
          "TagName": "Image Caption",
          "X": 861,
          "Y": 627,
          "W": 98,
          "H": 47,
          "ZoneId": "30_09_2022_204_002_011"
        }
      ]
    },
    {
      "ArticleName": "30_09_2022_204_003_toim",
      "Zones": [
        {
          "TagName": "Advertisement",
          "X": 25,
          "Y": 923,
          "W": 369,
          "H": 291,
          "ZoneId": "30_09_2022_204_003_002"
        }
      ]
    },
    {
      "ArticleName": "30_09_2022_204_004_toim",
      "Zones": [
        {
          "TagName": "Article Title",
          "X": 20,
          "Y": 701,
          "W": 310,
          "H": 156,
          "ZoneId": "30_09_2022_204_004_002"
        },
        {
          "TagName": "Article Body",
          "X": 406,
          "Y": 857,
          "W": 162,
          "H": 168,
          "ZoneId": "30_09_2022_204_004_003"
        },
        {
          "TagName": "Photographs",
          "X": 299,
          "Y": 701,
          "W": 268,
          "H": 152,
          "ZoneId": "30_09_2022_204_004_004"
        },
        {
          "TagName": "Image Caption",
          "X": 355,
          "Y": 824,
          "W": 181,
          "H": 31,
          "ZoneId": "30_09_2022_204_004_005"
        }
      ]
    },
    {
      "ArticleName": "30_09_2022_204_005_toim",
      "Zones": [
        {
          "TagName": "Advertisement",
          "X": 25,
          "Y": 1219,
          "W": 370,
          "H": 290,
          "ZoneId": "30_09_2022_204_005_003"
        }
      ]
    },
    {
      "ArticleName": "30_09_2022_204_008_toim",
      "Zones": [
        {
          "TagName": "Article Title",
          "X": 694,
          "Y": 68,
          "W": 263,
          "H": 27,
          "ZoneId": "30_09_2022_204_008_001"
        },
        {
          "TagName": "Information",
          "X": 583,
          "Y": 61,
          "W": 378,
          "H": 433,
          "ZoneId": "30_09_2022_204_008_002"
        }
      ]
    },
    {
      "ArticleName": "30_09_2022_204_009_toim",
      "Zones": [
        {
          "TagName": "Article Title",
          "X": 454,
          "Y": 20,
          "W": 92,
          "H": 24,
          "ZoneId": "30_09_2022_204_009_002"
        },
        {
          "TagName": "Information",
          "X": 18,
          "Y": 8,
          "W": 954,
          "H": 41,
          "ZoneId": "30_09_2022_204_009_003"
        }
      ]
    },
    {
      "ArticleName": "30_09_2022_204_017_toim",
      "Zones": [
        {
          "TagName": "Article Title",
          "X": 407,
          "Y": 1039,
          "W": 255,
          "H": 170,
          "ZoneId": "30_09_2022_204_017_001"
        },
        {
          "TagName": "Article Body",
          "X": 719,
          "Y": 1259,
          "W": 140,
          "H": 102,
          "ZoneId": "30_09_2022_204_017_002"
        },
        {
          "TagName": "Photographs",
          "X": 413,
          "Y": 1204,
          "W": 186,
          "H": 163,
          "ZoneId": "30_09_2022_204_017_003"
        },
        {
          "TagName": "Photographs",
          "X": 592,
          "Y": 1243,
          "W": 127,
          "H": 140,
          "ZoneId": "30_09_2022_204_017_005"
        },
        {
          "TagName": "Photographs",
          "X": 662,
          "Y": 1035,
          "W": 301,
          "H": 215,
          "ZoneId": "30_09_2022_204_017_007"
        },
        {
          "TagName": "Photographs",
          "X": 414,
          "Y": 1366,
          "W": 257,
          "H": 129,
          "ZoneId": "30_09_2022_204_017_009"
        },
        {
          "TagName": "Photographs",
          "X": 676,
          "Y": 1360,
          "W": 179,
          "H": 134,
          "ZoneId": "30_09_2022_204_017_011"
        },
        {
          "TagName": "Photographs",
          "X": 859,
          "Y": 1258,
          "W": 102,
          "H": 236,
          "ZoneId": "30_09_2022_204_017_013"
        },
        {
          "TagName": "Image Caption",
          "X": 594,
          "Y": 1209,
          "W": 66,
          "H": 40,
          "ZoneId": "30_09_2022_204_017_004"
        },
        {
          "TagName": "Image Caption",
          "X": 595,
          "Y": 1282,
          "W": 66,
          "H": 36,
          "ZoneId": "30_09_2022_204_017_006"
        },
        {
          "TagName": "Image Caption",
          "X": 759,
          "Y": 1063,
          "W": 75,
          "H": 41,
          "ZoneId": "30_09_2022_204_017_008"
        },
        {
          "TagName": "Image Caption",
          "X": 413,
          "Y": 1490,
          "W": 194,
          "H": 20,
          "ZoneId": "30_09_2022_204_017_010"
        },
        {
          "TagName": "Image Caption",
          "X": 675,
          "Y": 1488,
          "W": 167,
          "H": 23,
          "ZoneId": "30_09_2022_204_017_012"
        },
        {
          "TagName": "Image Caption",
          "X": 859,
          "Y": 1489,
          "W": 111,
          "H": 22,
          "ZoneId": "30_09_2022_204_017_014"
        }
      ]
    },
    {
      "ArticleName": "30_09_2022_204_018_toim",
      "Zones": [
        {
          "TagName": "Column Title",
          "X": 25,
          "Y": 250,
          "W": 190,
          "H": 103,
          "ZoneId": "30_09_2022_204_018_002"
        },
        {
          "TagName": "Article Title",
          "X": 18,
          "Y": 47,
          "W": 552,
          "H": 205,
          "ZoneId": "30_09_2022_204_018_001"
        },
        {
          "TagName": "Article Body",
          "X": 24,
          "Y": 370,
          "W": 186,
          "H": 142,
          "ZoneId": "30_09_2022_204_018_004"
        },
        {
          "TagName": "Article Body",
          "X": 213,
          "Y": 459,
          "W": 191,
          "H": 235,
          "ZoneId": "30_09_2022_204_018_005"
        },
        {
          "TagName": "Photographs",
          "X": 129,
          "Y": 542,
          "W": 199,
          "H": 155,
          "ZoneId": "30_09_2022_204_018_006"
        },
        {
          "TagName": "Photographs",
          "X": 216,
          "Y": 254,
          "W": 354,
          "H": 182,
          "ZoneId": "30_09_2022_204_018_007"
        },
        {
          "TagName": "Photographs",
          "X": 383,
          "Y": 438,
          "W": 185,
          "H": 214,
          "ZoneId": "30_09_2022_204_018_009"
        },
        {
          "TagName": "Author",
          "X": 21,
          "Y": 351,
          "W": 185,
          "H": 20,
          "ZoneId": "30_09_2022_204_018_003"
        },
        {
          "TagName": "Image Caption",
          "X": 213,
          "Y": 420,
          "W": 164,
          "H": 36,
          "ZoneId": "30_09_2022_204_018_008"
        },
        {
          "TagName": "Image Caption",
          "X": 397,
          "Y": 653,
          "W": 174,
          "H": 42,
          "ZoneId": "30_09_2022_204_018_010"
        },
        {
          "TagName": "Lead",
          "X": 25,
          "Y": 517,
          "W": 215,
          "H": 180,
          "ZoneId": "30_09_2022_204_018_011"
        }
      ]
    }
  ]
}